[
  {
    "order": {
      "amount": "10",
      "currency_code": "USD",
      "fullName": "mm",
      "cardName": "mm",
      "cardNumber": "5110923737126143",
      "cardExpiry": "08/2027",
      "cardCvv": "123"
    },
    "timestamp": "2024-02-28T21:31:25.117Z"
  },
  {
    "order": {
      "amount": "10",
      "currency_code": "USD",
      "fullName": "mm",
      "cardName": "mm",
      "cardNumber": "5110923737126143",
      "cardExpiry": "08/2027",
      "cardCvv": "123"
    },
    "timestamp": "2024-02-28T21:36:02.444Z"
  }
]